README.md
setup.cfg
setup.py
jjdist/Binomialdistribution.py
jjdist/Gaussiandistribution.py
jjdist/Generaldistribution.py
jjdist/__init__.py
jjdist.egg-info/PKG-INFO
jjdist.egg-info/SOURCES.txt
jjdist.egg-info/dependency_links.txt
jjdist.egg-info/not-zip-safe
jjdist.egg-info/top_level.txt